[
  {
    "id": "33",
    "name": "Justen Michael Watkins",
    "bio": "Convicted for social activism.",
    "profile_link": "#",
    "image_url": "/pictures/WATKINS_JUSTEN.png",
    "state": "MI"
  },
  {
    "id": "24",
    "name": "Dustin H Heathman",
    "bio": "Jailed for exposing corruption.",
    "profile_link": "#",
    "image_url": "/pictures/HEATHMAN_DUSTIN.png",
    "state": "FL"
  },
  {
    "id": "28",
    "name": "Travis McMichael",
    "bio": "Charged for reporting war crimes.",
    "profile_link": "#",
    "image_url": "/pictures/MCCHEMICHL_TRAVIS.png",
    "state": "GA"
  }
]
